repka/__init__.py
repka/api.py
repka/json_.py
repka/repositories/__init__.py
repka/repositories/aiopg_.py
repka/repositories/base.py
repka/repositories/fake.py
repka/repositories/queries.py
repka/utils.py
repka-3.2.0.dist-info/WHEEL
repka-3.2.0.dist-info/METADATA
repka-3.2.0.dist-info/RECORD
