Metadata-Version: 2.1
Name: repka
Version: 3.2.0
Summary: Python repository pattern implementation
Home-page: https://github.com/potykion/repka
License: MIT
Author: potykion
Author-email: potykion@gmail.com
Requires-Python: >=3.7,<4.0
Classifier: License :: OSI Approved :: MIT License
Classifier: Programming Language :: Python :: 3
Classifier: Programming Language :: Python :: 3.7
Classifier: Programming Language :: Python :: 3.8
Classifier: Programming Language :: Python :: 3.9
Requires-Dist: aiopg (>=1,<2)
Requires-Dist: pydantic (>=1.0,<2.0)
Requires-Dist: sqlalchemy (>=1.3,<2.0)
Requires-Dist: typing_inspect (>=0.5.0,<0.6.0)
Project-URL: Repository, https://github.com/potykion/repka
